{
    "name": "Fornecedor",
    "fields": [
        {
            "fieldName": "cnpj",
            "fieldType": "String",
            "fieldValidateRules": [
                "minlength",
                "maxlength",
                "unique",
                "required"
            ],
            "fieldValidateRulesMinlength": 14,
            "fieldValidateRulesMaxlength": 14
        },
        {
            "fieldName": "razaoSocial",
            "fieldType": "String",
            "fieldValidateRules": [
                "maxlength",
                "required"
            ],
            "fieldValidateRulesMaxlength": 255
        },
        {
            "fieldName": "nomeFantasia",
            "fieldType": "String",
            "fieldValidateRules": [
                "maxlength",
                "required"
            ],
            "fieldValidateRulesMaxlength": 120
        }
    ],
    "relationships": [],
    "changelogDate": "20200618123157",
    "entityTableName": "fornecedor",
    "dto": "mapstruct",
    "pagination": "pagination",
    "service": "serviceClass",
    "jpaMetamodelFiltering": false,
    "fluentMethods": true,
    "readOnly": false,
    "clientRootFolder": "madresuprimentos",
    "applications": "*",
    "skipClient": true,
    "microserviceName": "madresuprimentos"
}